{
  "type": "CoreBlock",
  "name": "[#ff66]Regis",
  "description": "The Regis Core Builds a Delver to help defend it",
  "details": "",
  "size": 4,
  "researchCostMultiplier": 0.4,
  "health": 10000,
  "itemCapacity": 10000,
  "requirements": [
    {
      "item": "copper",
      "amount": 5000
    },
    {
      "item": "lead",
      "amount": 5000
    },
    {
      "item": "silicon",
      "amount": 5000
    },
    {
      "item": "titanium",
      "amount": 5000
    },
    {
      "item": "thorium",
      "amount": 5000
    },
    {
      "item": "molten-alloy",
      "amount": 1000
    }
  ],
  "category": "effect",
  "research": "molten-alloy",
  "unitType": "z-delver",
  "unitCapModifier": 25
}
